{
  "schemaVersion": 1,
  "id": "butter-framedupe",
  "version": "${version}",
  "name": "AutoFrameDupe",
  "description": "AutoFrameDupe from LeuxBackdoor",
  "authors": [
    "Butter"
  ],
  "contact": {
    "repo": "https://github.com/MeteorDevelopment/meteor-addon-template"
  },
  "icon": "assets/template/icon.png",
  "environment": "client",
  "entrypoints": {
    "meteor": [
      "me.butter.addon.AutoFrameDupeAddon"
    ]
  },
  "custom": {
    "meteor-client:color": "225,25,25"
  },
  "depends": {
    "java": ">=21",
    "minecraft": ["${mc_version}"],
    "meteor-client": "*"
  }
}
